setup.py
lzmodelndata.egg-info/PKG-INFO
lzmodelndata.egg-info/SOURCES.txt
lzmodelndata.egg-info/dependency_links.txt
lzmodelndata.egg-info/requires.txt
lzmodelndata.egg-info/top_level.txt
lzpackage/__init__.py
lzpackage/sample.py