Metadata-Version: 2.1
Name: lzmodelndata
Version: 0.1
Summary: model data package
Author: lz
Author-email: jhs012@gmail.com
